{
    "codes": [
        {
            "code": "C9F2H5J8",
            "duration_hms": "168:00:00",
            "duration_ms": 604800000,
            "status": "active",
            "max_uses": 1,
            "current_uses": 0,
            "first_activated_at": 0
        },
        {
            "code": "B1D4G7K0",
            "duration_hms": "168:00:00",
            "duration_ms": 604800000,
            "status": "active",
            "max_uses": 1,
            "current_uses": 0,
            "first_activated_at": 0
        },
        {
            "code": "M3P6R9T2",
            "duration_hms": "168:00:00",
            "duration_ms": 604800000,
            "status": "active",
            "max_uses": 1,
            "current_uses": 0,
            "first_activated_at": 0
        },
        {
            "code": "S5V8X1Z4",
            "duration_hms": "168:00:00",
            "duration_ms": 604800000,
            "status": "active",
            "max_uses": 1,
            "current_uses": 0,
            "first_activated_at": 0
        },
        {
            "code": "W7Y0A2C5",
            "duration_hms": "168:00:00",
            "duration_ms": 604800000,
            "status": "active",
            "max_uses": 1,
            "current_uses": 0,
            "first_activated_at": 0
        }
                {
            "code": "W7Y0AS2C5",
            "duration_hms": "168:00:00",
            "duration_ms": 604800000,
            "status": "active",
            "max_uses": 1,
            "current_uses": 0,
            "first_activated_at": 0
                }
    ]
}
